parse.py
parse-1.19.0.post0.dist-info/LICENSE
parse-1.19.0.post0.dist-info/METADATA
parse-1.19.0.post0.dist-info/WHEEL
parse-1.19.0.post0.dist-info/top_level.txt
parse-1.19.0.post0.dist-info/RECORD
