Metadata-Version: 2.1
Name: parse
Version: 1.19.0.post0
Summary: parse() is the opposite of format()
Home-page: https://github.com/r1chardj0n3s/parse
Author: Richard Jones
Author-email: richard@python.org
Classifier: Environment :: Web Environment
Classifier: Intended Audience :: Developers
Classifier: Programming Language :: Python :: 3.4
Classifier: Programming Language :: Python :: 3.5
Classifier: Programming Language :: Python :: 3.6
Classifier: Programming Language :: Python :: 3.7
Classifier: Programming Language :: Python :: 3.8
Classifier: Topic :: Software Development :: Code Generators
Classifier: Topic :: Software Development :: Libraries :: Python Modules
Classifier: License :: OSI Approved :: BSD License
License-File: LICENSE
